athenaSQL/__init__.py
athenaSQL/athena.py
athenaSQL/athena_table.py
athenaSQL/column.py
athenaSQL/column_type.py
athenaSQL/data_type.py
athenaSQL/errors.py
athenaSQL/functions/__init__.py
athenaSQL/functions/aggregate.py
athenaSQL/functions/conditional.py
athenaSQL/functions/date_time.py
athenaSQL/functions/functions.py
athenaSQL/functions/math.py
athenaSQL/functions/regular_expression.py
athenaSQL/functions/string.py
athenaSQL/functions/window.py
athenaSQL/operator_mixin.py
athenaSQL/orders.py
athenaSQL/queries/__init__.py
athenaSQL/queries/create.py
athenaSQL/queries/create_as.py
athenaSQL/queries/cte.py
athenaSQL/queries/insert.py
athenaSQL/queries/query_abc.py
athenaSQL/queries/select.py
athenaSQL/queries/unload.py
athenaSQL/queries/window.py
athenaSQL/utils.py
athenasql-0.1.1.dist-info/LICENSE
athenasql-0.1.1.dist-info/METADATA
athenasql-0.1.1.dist-info/WHEEL
athenasql-0.1.1.dist-info/RECORD
