Metadata-Version: 2.1
Name: athenaSql
Version: 0.1.1
Summary: SQL builder for AWS Athena, inspired by sparkSQL
Home-page: https://github.com/nabilseid/athenaSQL
License: MIT
Keywords: packaging,athena,sql,athenaSQL
Author: Nabil Seid
Author-email: nabeelseid@gmail.com
Requires-Python: >=3.7,<4.0
Classifier: License :: OSI Approved :: MIT License
Classifier: Operating System :: OS Independent
Classifier: Programming Language :: Python :: 3
Classifier: Programming Language :: Python :: 3.7
Classifier: Programming Language :: Python :: 3.8
Classifier: Programming Language :: Python :: 3.9
Classifier: Programming Language :: Python :: 3.10
Classifier: Programming Language :: Python :: 3.11
Classifier: Programming Language :: Python :: 3.12
Classifier: Programming Language :: Python :: 3.13
Requires-Dist: awswrangler (>=3.4.2,<4.0.0)
Requires-Dist: jinja2 (>=3.1.2,<4.0.0)
Project-URL: Documentation, https://github.com/nabilseid/athenaSQL/docs
Project-URL: Repository, https://github.com/nabilseid/athenaSQL
